pyfuzz_web/__init__.py
pyfuzz_web/pyfuzz.py
pyfuzz_web/lists/asp.txt
pyfuzz_web/lists/directories.txt
pyfuzz_web/lists/others.txt
pyfuzz_web/lists/php.txt
pyfuzz_web/lists/sharepoint.txt
pyfuzz_web/lists/short.txt
pyfuzz_web-1.1.1.post1.dist-info/LICENSE
pyfuzz_web-1.1.1.post1.dist-info/METADATA
pyfuzz_web-1.1.1.post1.dist-info/WHEEL
pyfuzz_web-1.1.1.post1.dist-info/entry_points.txt
pyfuzz_web-1.1.1.post1.dist-info/top_level.txt
pyfuzz_web-1.1.1.post1.dist-info/RECORD
