Metadata-Version: 2.2
Name: pyfuzz-web
Version: 1.1.1.post1
Summary: Comprehensive web path scanner tool designed to facilitate penetration testing and web application security assessment
Author: Ayoob Ali
License: MIT
Project-URL: Homepage, http://ayoobali.github.io/pyfuzz/
License-File: LICENSE
